pysdrradio/__init__.py
pysdrradio/decoder.py
pysdrradio/radio.py
pysdrradio-0.0.3.dist-info/LICENSE
pysdrradio-0.0.3.dist-info/METADATA
pysdrradio-0.0.3.dist-info/WHEEL
pysdrradio-0.0.3.dist-info/top_level.txt
pysdrradio-0.0.3.dist-info/RECORD
