Metadata-Version: 2.1
Name: pysdrradio
Version: 0.0.3
Summary: RTL-SDR FM Radio
Author-email: Brian Simpokolwe <briansimpokolwe@gmail.com>
Project-URL: Homepage, https://github.com/briansimpo/pysdrradio
Project-URL: Bug Tracker, https://github.com/briansimpo/pysdrradio/issues
Classifier: Programming Language :: Python :: 3
Classifier: License :: OSI Approved :: MIT License
Classifier: Operating System :: OS Independent
Requires-Python: >=3.7
License-File: LICENSE
Requires-Dist: numpy >=1.25.0
Requires-Dist: matplotlib >=3.7.1
Requires-Dist: scipy >=1.10.1
Requires-Dist: pyaudio >=0.2.13
Requires-Dist: pydub >=0.25.1
Requires-Dist: pyrtlsdr >=0.3.0
Requires-Dist: pyrtlsdrlib >=0.0.2
